LICENSE
MANIFEST.in
README.md
requirements.txt
setup.py
climkit/Cquiver.py
climkit/K_Mean.py
climkit/TN_WaveActivityFlux.py
climkit/__init__.py
climkit/average_filter.py
climkit/corr_reg.py
climkit/data_read.py
climkit/draw_plot.py
climkit/filter.py
climkit/force_file.py
climkit/lead_lag_corr.py
climkit/lonlat_transform.py
climkit/masked.py
climkit/move_detrend.py
climkit/pre_whitening.py
climkit/significance_test.py
climkit/specx_anal.py
climkit/sub_adjust.py
climkit/temperature_budget.py
climkit/wavelet.py
climkit.egg-info/PKG-INFO
climkit.egg-info/SOURCES.txt
climkit.egg-info/dependency_links.txt
climkit.egg-info/requires.txt
climkit.egg-info/top_level.txt
test/__init__.py
test/frc_draw.py
test/lbm.py
test/f2py/__init__.py
test/f2py/copy.py
test/f2py/dim.py
test/f2py/dsphe.py
test/f2py/ufftp.py
test/f2py/usphe.py
test/f2py/xabort.py