Metadata-Version: 2.4
Name: climkit
Version: 0.1.1
Summary: Some tool function package for Climate
Home-page: https://github.com/hhhopsong/climkit
Author: Tingyang Song
Author-email: 1057422494@qq.com
Classifier: Programming Language :: Python :: 3
Requires-Python: >=3.8
License-File: LICENSE
Requires-Dist: numpy>=1.26
Requires-Dist: pandas>=2.2
Requires-Dist: scipy>=1.12
Requires-Dist: xarray>=2024.1
Requires-Dist: netCDF4>=1.6
Requires-Dist: cftime>=1.6
Requires-Dist: bottleneck>=1.3
Requires-Dist: matplotlib>=3.8
Requires-Dist: metpy>=1.6
Requires-Dist: scikit-learn>=1.4
Requires-Dist: joblib>=1.3
Requires-Dist: cartopy>=0.22
Requires-Dist: shapely>=1.0
Requires-Dist: pyproj>=3.6
Requires-Dist: xgrads>=0.2.0
Requires-Dist: cmaps>=1.5
Requires-Dist: func_timeout>=1.0
Requires-Dist: numba>=0.53
Requires-Dist: salem>=0.2
Requires-Dist: eofs>=1.0
Requires-Dist: geopandas>=0.10
Requires-Dist: pymannkendall>=1.0
Requires-Dist: statsmodels>=0.9
Requires-Dist: pycwt
Requires-Dist: alive_progress
Requires-Dist: pyproj>=3.6.1
Dynamic: author
Dynamic: author-email
Dynamic: classifier
Dynamic: description
Dynamic: description-content-type
Dynamic: home-page
Dynamic: license-file
Dynamic: requires-dist
Dynamic: requires-python
Dynamic: summary
